nepali_normalizer/__init__.py
nepali_normalizer/normalizer.py
nepali_normalizer-0.1.1.dist-info/LICENSE
nepali_normalizer-0.1.1.dist-info/METADATA
nepali_normalizer-0.1.1.dist-info/WHEEL
nepali_normalizer-0.1.1.dist-info/top_level.txt
nepali_normalizer-0.1.1.dist-info/RECORD
