Metadata-Version: 2.1
Name: nepali-normalizer
Version: 0.1.1
Summary: Advanced normalization toolkit for Nepali text processing
Home-page: https://github.com/FancyCodeMaster/nepali-normalizer
Author: FancyCodeMaster
Author-email: fancycodemaster@gmail.com
License: UNKNOWN
Platform: UNKNOWN
Classifier: Programming Language :: Python :: 3
Classifier: License :: OSI Approved :: MIT License
Classifier: Operating System :: OS Independent
Requires-Python: >=3.10
License-File: LICENSE
Requires-Dist: indic-nlp-library>=0.81
Requires-Dist: regex
